openupgradelib/__init__.py
openupgradelib/openupgrade.py
openupgradelib/openupgrade_120.py
openupgradelib/openupgrade_130.py
openupgradelib/openupgrade_140.py
openupgradelib/openupgrade_160.py
openupgradelib/openupgrade_180.py
openupgradelib/openupgrade_70.py
openupgradelib/openupgrade_80.py
openupgradelib/openupgrade_90.py
openupgradelib/openupgrade_merge_records.py
openupgradelib/openupgrade_tools.py
openupgradelib-3.12.0.dist-info/licenses/AUTHORS.rst
openupgradelib-3.12.0.dist-info/licenses/LICENSE
openupgradelib-3.12.0.dist-info/METADATA
openupgradelib-3.12.0.dist-info/WHEEL
openupgradelib-3.12.0.dist-info/top_level.txt
openupgradelib-3.12.0.dist-info/RECORD
